{
    "headers": [ "Nombre", "12Uvas", "Reg. AdaByron", "Nac. AdaByron", "Curso CP", "Codeforces", "Clasificatorio", "Puntos" ],
    "rows": [
        {
            "Nombre": { "content": "Iván Coello Rivera" },
            "12Uvas": { "content": "5", "position":"50"},
            "Reg. AdaByron": { "content": "10", "position":"2" },
            "Nac. AdaByron": { "content": "10", "position":"-" },
            "Curso CP": { "content": "-" },
            "Codeforces": { "content": "-" },
            "Clasificatorio": { "content": "-", "position": "-" },
            "skips": false
        },
        {
            "Nombre": { "content": "Jose Manuel Fernández Moreno" },
            "12Uvas": { "content": "5", "position":"73"},
            "Reg. AdaByron": { "content": "10", "position":"2" },
            "Nac. AdaByron": { "content": "10", "position":"-" },
            "Curso CP": { "content": "-" },
            "Codeforces": { "content": "3" },
            "Clasificatorio": { "content": "-", "position": "-" },
            "skips": false
        },
        {
            "Nombre": { "content": "Iván Dorado Alegria" },
            "12Uvas": { "content": "5", "position":"130"},
            "Reg. AdaByron": { "content": "-", "position":"-" },
            "Nac. AdaByron": { "content": "-", "position":"-" },
            "Curso CP": { "content": "-" },
            "Codeforces": { "content": "-" },
            "Clasificatorio": { "content": "-" },
            "skips": false
        },
        {
            "Nombre": { "content": "Alberto Saoner Plomer" },
            "12Uvas": { "content": "-" },
            "Reg. AdaByron": { "content": "10", "position":"34" },
            "Nac. AdaByron": { "content": "-", "position":"-" },
            "Curso CP": { "content": "-" },
            "Codeforces": { "content": "-" },
            "Clasificatorio": { "content": "-", "position": "-" },
            "skips": false
        },
        {
            "Nombre": { "content": "Alejandro González Blanco" },
            "12Uvas": { "content": "-" },
            "Reg. AdaByron": { "content": "10", "position":"21" },
            "Nac. AdaByron": { "content": "-", "position":"-" },
            "Curso CP": { "content": "5" },
            "Codeforces": { "content": "-" },
            "Clasificatorio": { "content": "-", "position": "-" },
            "skips": false
        },
        {
            "Nombre": { "content": "Álvaro Merinero González" },
            "12Uvas": { "content": "-" },
            "Reg. AdaByron": { "content": "10", "position":"34" },
            "Nac. AdaByron": { "content": "-", "position":"-" },
            "Curso CP": { "content": "5" },
            "Codeforces": { "content": "-" },
            "Clasificatorio": { "content": "-", "position": "-" },
            "skips": false
        },
        {
            "Nombre": { "content": "Christian Perea Reina" },
            "12Uvas": { "content": "-" },
            "Reg. AdaByron": { "content": "10", "position":"27" },
            "Nac. AdaByron": { "content": "-", "position":"-" },
            "Curso CP": { "content": "5" },
            "Codeforces": { "content": "-" },
            "Clasificatorio": { "content": "-", "position": "-" },
            "skips": false
        },
        {
            "Nombre": { "content": "Daniel Montes Jiménez" },
            "12Uvas": { "content": "-" },
            "Reg. AdaByron": { "content": "10", "position":"15" },
            "Nac. AdaByron": { "content": "-", "position":"-" },
            "Curso CP": { "content": "5" },
            "Codeforces": { "content": "-" },
            "Clasificatorio": { "content": "-", "position": "-" },
            "skips": false
        },
        {
            "Nombre": { "content": "Daniel Quijano Alonso" },
            "12Uvas": { "content": "-" },
            "Reg. AdaByron": { "content": "10", "position":"30" },
            "Nac. AdaByron": { "content": "-", "position":"-" },
            "Curso CP": { "content": "5" },
            "Codeforces": { "content": "-" },
            "Clasificatorio": { "content": "-", "position": "-" },
            "skips": false
        },
        {
            "Nombre": { "content": "David Arévalo Rey" },
            "12Uvas": { "content": "-" },
            "Reg. AdaByron": { "content": "10", "position":"13" },
            "Nac. AdaByron": { "content": "-", "position":"-" },
            "Curso CP": { "content": "5" },
            "Codeforces": { "content": "-" },
            "Clasificatorio": { "content": "-", "position": "-" },
            "skips": false
        },
        {
            "Nombre": { "content": "David Constantin Margarint" },
            "12Uvas": { "content": "-" },
            "Reg. AdaByron": { "content": "-", "position":"-" },
            "Nac. AdaByron": { "content": "-", "position":"-" },
            "Curso CP": { "content": "5" },
            "Codeforces": { "content": "-" },
            "Clasificatorio": { "content": "-", "position": "-" },
            "skips": false
        },
        {
            "Nombre": { "content": "Gabriel De Miguel García" },
            "12Uvas": { "content": "-" },
            "Reg. AdaByron": { "content": "-", "position":"-" },
            "Nac. AdaByron": { "content": "-", "position":"-" },
            "Curso CP": { "content": "5" },
            "Codeforces": { "content": "-" },
            "Clasificatorio": { "content": "-", "position": "-" },
            "skips": false
        },
        {
            "Nombre": { "content": "Iván Gómez Molano" },
            "12Uvas": { "content": "-" },
            "Reg. AdaByron": { "content": "10", "position":"27" },
            "Nac. AdaByron": { "content": "-", "position":"-" },
            "Curso CP": { "content": "5" },
            "Codeforces": { "content": "-" },
            "Clasificatorio": { "content": "-", "position": "-" },
            "skips": false
        },
        {
            "Nombre": { "content": "Jorge Camacho Mejías" },
            "12Uvas": { "content": "-" },
            "Reg. AdaByron": { "content": "10", "position":"13" },
            "Nac. AdaByron": { "content": "-", "position":"-" },
            "Curso CP": { "content": "5" },
            "Codeforces": { "content": "-" },
            "Clasificatorio": { "content": "-", "position": "-" },
            "skips": false
        },
        {
            "Nombre": { "content": "Jose Barrios Peguero" },
            "12Uvas": { "content": "-" },
            "Reg. AdaByron": { "content": "-", "position":"-" },
            "Nac. AdaByron": { "content": "-", "position":"-" },
            "Curso CP": { "content": "5" },
            "Codeforces": { "content": "-" },
            "Clasificatorio": { "content": "-", "position": "-" },
            "skips": false
        },
        {
            "Nombre": { "content": "Laura Alejandra Sánchez Fernández" },
            "12Uvas": { "content": "-" },
            "Reg. AdaByron": { "content": "-", "position":"-" },
            "Nac. AdaByron": { "content": "-", "position":"-" },
            "Curso CP": { "content": "5" },
            "Codeforces": { "content": "-" },
            "Clasificatorio": { "content": "-", "position": "-" },
            "skips": false
        },
        {
            "Nombre": { "content": "Manuel Rey Carbonell" },
            "12Uvas": { "content": "-" },
            "Reg. AdaByron": { "content": "10", "position":"27" },
            "Nac. AdaByron": { "content": "-", "position":"-" },
            "Curso CP": { "content": "5" },
            "Codeforces": { "content": "-" },
            "Clasificatorio": { "content": "-", "position": "-" },
            "skips": false
        },
        {
            "Nombre": { "content": "Mengying Xia Ruan" },
            "12Uvas": { "content": "-" },
            "Reg. AdaByron": { "content": "10", "position":"30" },
            "Nac. AdaByron": { "content": "-", "position":"-" },
            "Curso CP": { "content": "-" },
            "Codeforces": { "content": "-" },
            "Clasificatorio": { "content": "-", "position": "-" },
            "skips": false
        },
        {
            "Nombre": { "content": "Olga Somalo Serrano" },
            "12Uvas": { "content": "-" },
            "Reg. AdaByron": { "content": "10", "position":"13" },
            "Nac. AdaByron": { "content": "-", "position":"-" },
            "Curso CP": { "content": "5" },
            "Codeforces": { "content": "-" },
            "Clasificatorio": { "content": "-", "position": "-" },
            "skips": false
        },
        {
            "Nombre": { "content": "Pablo Sainz López" },
            "12Uvas": { "content": "-" },
            "Reg. AdaByron": { "content": "10", "position":"21" },
            "Nac. AdaByron": { "content": "-", "position":"-" },
            "Curso CP": { "content": "-" },
            "Codeforces": { "content": "-" },
            "Clasificatorio": { "content": "-", "position": "-" },
            "skips": false
        },
        {
            "Nombre": { "content": "Rafael Sánchez Vaquero" },
            "12Uvas": { "content": "-" },
            "Reg. AdaByron": { "content": "-", "position":"-" },
            "Nac. AdaByron": { "content": "-", "position":"-" },
            "Curso CP": { "content": "5" },
            "Codeforces": { "content": "-" },
            "Clasificatorio": { "content": "-", "position": "-" },
            "skips": false
        },
        {
            "Nombre": { "content": "Raúl Luaces Salamanca" },
            "12Uvas": { "content": "-" },
            "Reg. AdaByron": { "content": "10", "position":"30" },
            "Nac. AdaByron": { "content": "-", "position":"-" },
            "Curso CP": { "content": "-" },
            "Codeforces": { "content": "-" },
            "Clasificatorio": { "content": "-", "position": "-" },
            "skips": false
        },
        {
            "Nombre": { "content": "Weisheng Zheng" },
            "12Uvas": { "content": "-" },
            "Reg. AdaByron": { "content": "10", "position":"21" },
            "Nac. AdaByron": { "content": "-", "position":"-" },
            "Curso CP": { "content": "-" },
            "Codeforces": { "content": "3" },
            "Clasificatorio": { "content": "-", "position": "-" },
            "skips": false
        },
        {
            "Nombre": { "content": "Javier Almendro Mirat" },
            "12Uvas": { "content": "-" },
            "Reg. AdaByron": { "content": "-", "position":"-" },
            "Nac. AdaByron": { "content": "-", "position":"-" },
            "Curso CP": { "content": "5" },
            "Codeforces": { "content": "-" },
            "Clasificatorio": { "content": "-", "position": "-" },
            "skips": false
        },
        {
            "Nombre": { "content": "Ricardo Michael Sucunuta Macas" },
            "12Uvas": { "content": "-" },
            "Reg. AdaByron": { "content": "-", "position":"-" },
            "Nac. AdaByron": { "content": "-", "position":"-" },
            "Curso CP": { "content": "5" },
            "Codeforces": { "content": "-" },
            "Clasificatorio": { "content": "-", "position": "-" },
            "skips": false
        },
        {
            "Nombre": { "content": "Iván Canosa Delgado" },
            "12Uvas": { "content": "-" },
            "Reg. AdaByron": { "content": "-", "position":"-" },
            "Nac. AdaByron": { "content": "-", "position":"-" },
            "Curso CP": { "content": "5" },
            "Codeforces": { "content": "-" },
            "Clasificatorio": { "content": "-", "position": "-" },
            "skips": false
        },
        {
            "Nombre": { "content": "Pablo Picurelli Ortiz" },
            "12Uvas": { "content": "-" },
            "Reg. AdaByron": { "content": "10", "position":"34" },
            "Nac. AdaByron": { "content": "-", "position":"-" },
            "Curso CP": { "content": "5" },
            "Codeforces": { "content": "-" },
            "Clasificatorio": { "content": "-", "position": "-" },
            "skips": false
        },
        {
            "Nombre": { "content": "Jonathan Javier Flores Naranjo" },
            "12Uvas": { "content": "-" },
            "Reg. AdaByron": { "content": "-", "position":"-" },
            "Nac. AdaByron": { "content": "-", "position":"-" },
            "Curso CP": { "content": "5" },
            "Codeforces": { "content": "-" },
            "Clasificatorio": { "content": "-", "position": "-" },
            "skips": false
        },
        {
            "Nombre": { "content": "Nihad Rbaa Hmini" },
            "12Uvas": { "content": "-" },
            "Reg. AdaByron": { "content": "10", "position":"2" },
            "Nac. AdaByron": { "content": "10", "position":"-" },
            "Curso CP": { "content": "-" },
            "Codeforces": { "content": "-" },
            "Clasificatorio": { "content": "-", "position": "-" },
            "skips": false
        },
        {
            "Nombre": { "content": "Ivan Fallos Mora" },
            "12Uvas": { "content": "-" },
            "Reg. AdaByron": { "content": "10", "position":"15" },
            "Nac. AdaByron": { "content": "-", "position":"-" },
            "Curso CP": { "content": "-" },
            "Codeforces": { "content": "-" },
            "Clasificatorio": { "content": "-", "position": "-" },
            "skips": false
        },
        {
            "Nombre": { "content": "Christopher Steven Quishpe Vinueza" },
            "12Uvas": { "content": "-" },
            "Reg. AdaByron": { "content": "10", "position":"15" },
            "Nac. AdaByron": { "content": "-", "position":"-" },
            "Curso CP": { "content": "-" },
            "Codeforces": { "content": "-" },
            "Clasificatorio": { "content": "-", "position": "-" },
            "skips": false
        }
    ]
}
